river_extra/__init__.py
river_extra/__version__.py
river_extra/compat/pytorch.py
river_extra/ensemble/__init__.py
river_extra/ensemble/online_extra_trees.py
river_extra/metrics/__init__.py
river_extra/metrics/cluster/__init__.py
river_extra/metrics/cluster/base.py
river_extra/metrics/cluster/bic.py
river_extra/metrics/cluster/daviesbouldin.py
river_extra/metrics/cluster/generalized_dunn.py
river_extra/metrics/cluster/i_index.py
river_extra/metrics/cluster/ps.py
river_extra/metrics/cluster/r2.py
river_extra/metrics/cluster/rmsstd.py
river_extra/metrics/cluster/sd_validation.py
river_extra/metrics/cluster/separation.py
river_extra/metrics/cluster/ssb.py
river_extra/metrics/cluster/ssq_based.py
river_extra/metrics/cluster/ssw.py
river_extra/metrics/cluster/xiebeni.py
river_extra/metrics/kappa.py
river_extra/metrics/prevalence_threshold.py
river_extra/metrics/purity.py
river_extra/metrics/q0.py
river_extra/metrics/variation_info.py
river_extra/tree/nodes/__init__.py
river_extra/tree/nodes/et_nodes.py
river_extra/tree/splitter/__init__.py
river_extra/tree/splitter/random_splitter.py
river_extra-0.14.0.dist-info/LICENSE
river_extra-0.14.0.dist-info/WHEEL
river_extra-0.14.0.dist-info/METADATA
river_extra-0.14.0.dist-info/RECORD
