Metadata-Version: 2.1
Name: river-extra
Version: 0.14.0
Summary: Additional estimators for the River package
License: BSD-3
Author: MaxHalford
Author-email: maxhalford25@gmail.com
Requires-Python: >=3.6.1,<4.0
Classifier: License :: Other/Proprietary License
Classifier: Programming Language :: Python :: 3
Classifier: Programming Language :: Python :: 3.10
Classifier: Programming Language :: Python :: 3.7
Classifier: Programming Language :: Python :: 3.8
Classifier: Programming Language :: Python :: 3.9
Requires-Dist: river (==0.14.0)
